libfivepy/__init__.py
libfivepy/cgs.py
libfivepy/kernel.py
libfivepy/shapes.py
libfivepy/transforms.py
libfivepy/vector.py
libfivepy-0.1.dist-info/LICENSE
libfivepy-0.1.dist-info/METADATA
libfivepy-0.1.dist-info/WHEEL
libfivepy-0.1.dist-info/top_level.txt
libfivepy-0.1.dist-info/RECORD
