Metadata-Version: 2.1
Name: libfivepy
Version: 0.1
Summary: A CAD library based on libfive
Home-page: https://gitlab.com/rcmz0/libfivepy
Author: rcmz, mkeeter, stewart.milberger, traverse.da, just to name a few
Author-email: antoinerichermoz@gmail.com
License: MIT
Platform: UNKNOWN
Classifier: Programming Language :: Python :: 3
Classifier: License :: OSI Approved :: MIT License
